jupyter_notebook_gist/__init__.py
jupyter_notebook_gist/config.py
jupyter_notebook_gist/handlers.py
jupyter_notebook_gist/static/extension.js
jupyter_notebook_gist-0.4.0.dist-info/DESCRIPTION.rst
jupyter_notebook_gist-0.4.0.dist-info/METADATA
jupyter_notebook_gist-0.4.0.dist-info/RECORD
jupyter_notebook_gist-0.4.0.dist-info/WHEEL
jupyter_notebook_gist-0.4.0.dist-info/metadata.json
jupyter_notebook_gist-0.4.0.dist-info/top_level.txt
