Metadata-Version: 2.0
Name: jupyter-notebook-gist
Version: 0.4.0
Summary: Create a gist from the Jupyter Notebook UI
Home-page: https://github.com/mozilla/jupyter-notebook-gist
Author: Mozilla Firefox Data Platform
Author-email: fx-data-platform@mozilla.com
License: MPL2
Platform: UNKNOWN
Requires-Dist: ipython (>=4)
Requires-Dist: jupyter
Requires-Dist: notebook (>=4.2)
Requires-Dist: requests
Requires-Dist: widgetsnbextension
